{
    "operators": [
      {
        "id": "red_wolf",
        "name": "红狼（凯·席尔瓦）",
        "type": "突击",
        "skills": {
          "main": "动力外骨骼：超载模式提升移速、射速，击倒敌人后回血并延长持续时间。",
          "second": "三联装手炮：发射三颗榴弹，主要用于逼身位和补刀。",
          "throwable": "战术烟雾弹：短时烟雾遮蔽视野。",
          "passive": "战术滑铲：能进行快速滑铲。"
        },
        "background": "GTI北美分部突击干员，首个单兵动力外骨骼使用者，以速度和体力见长。",
        "suitable_for_players": {
          "鼠鼠 (避战/捡漏)": {
            "suitability": "B",
            "reason": "技能组偏向进攻与机动，对避战搜刮的直接帮助有限。",
            "strategy": "可利用滑铲和加速快速穿越危险区域，抢先进入次级资源点。烟雾弹用于紧急遮蔽撤退。",
            "core_advantage": "高机动性用于快速转点与规避。"
          },
          "堵撤离点/夺舍流 (蹲守/掠夺)": {
            "suitability": "S",
            "reason": "极强的单兵机动性与收割能力，完美契合偷袭、追击、夺舍后撤离的完整链条。",
            "strategy": "利用超载加速埋伏或发起偷袭；击杀后回血并延长加速，便于舔包后快速脱离战场。手炮可用于补刀或逼出掩体后的敌人。",
            "core_advantage": "击杀刷新加速与回血，是夺舍流的绝对核心发动机。"
          },
          "猛攻流 (正面作战)": {
            "suitability": "A",
            "reason": "正面提升团队突破速度与持续作战能力，是突击箭头之一。",
            "strategy": "开启超载带头冲锋，利用高射速和移速优势撕开防线。烟雾弹掩护团队推进或封锁敌方视野。",
            "core_advantage": "团队突击与持续作战的强力增益。"
          }
        }
      },
      {
        "id": "wei_long",
        "name": "威龙（王宇昊）",
        "type": "突击",
        "skills": {
          "main": "虎蹲炮：发射压缩空气弹击倒敌人，创造控制机会。",
          "second": "动力推进：快速朝指定方向推进10米，击倒敌人减少冷却。",
          "throwable": "磁吸炸弹：投掷后吸附在硬表面，对敌人和载具造成高伤害。",
          "passive": "动能辅助系统：使用技能或高处坠落后4秒内减伤并加速。"
        },
        "background": "原舰载机飞行员，高机动突击干员，擅长撕开防线、反载具。",
        "suitable_for_players": {
          "鼠鼠 (避战/捡漏)": {
            "suitability": "A",
            "reason": "强大的瞬间位移能力，能抢先抵达资源点或快速脱离危险。",
            "strategy": "落地使用推进抢先搜刮；遭遇敌人时用推进迅速拉开距离逃跑。",
            "core_advantage": "无与伦比的跑图与逃生能力。"
          },
          "堵撤离点/夺舍流 (蹲守/掠夺)": {
            "suitability": "A",
            "reason": "灵活的位移和强力控制技能，适合在复杂地形发起突袭。",
            "strategy": "利用推进快速占据有利埋伏点或发起偷袭；虎蹲炮击倒后轻松收割；磁吸炸弹封锁撤离点或车辆。",
            "core_advantage": "高机动突袭与控制。"
          },
          "猛攻流 (正面作战)": {
            "suitability": "S",
            "reason": "版本强势突击手，集位移、控制、爆发于一体，室内战与复杂地形战王者。",
            "strategy": "推进切入战场或规避火力；虎蹲炮控制关键敌人；磁吸炸弹攻坚或反载具。被动提供不错的生存容错。",
            "core_advantage": "全方位立体突击能力，猛攻队核心。"
          }
        }
      },
      {
        "id": "wuming",
        "name": "无名（埃利·德·蒙贝尔）",
        "type": "突击",
        "skills": {
          "main": "旋刃飞行器：自动追踪敌人造成伤害。",
          "second": "突破型闪光弹：致盲敌人。",
          "throwable": "静默潜袭：激活后缩小自身声音传播范围，并延长敌人用药和被救援时间。",
          "passive": "重伤延滞：使被自己击倒的敌人治疗和救援时间延长。"
        },
        "background": "原哈夫克杀手，摆脱控制后加入GTI，擅长隐蔽突袭与信息干扰。",
        "suitable_for_players": {
          "鼠鼠 (避战/捡漏)": {
            "suitability": "C",
            "reason": "技能组进攻性较强，静默潜袭对安静移动有帮助但非核心生存技能。",
            "strategy": "开启静默潜袭可以更安静地移动，避免惊动敌人。遭遇战时用闪光弹致盲逃跑。",
            "core_advantage": "移动声音减小，略微提升隐蔽性。"
          },
          "堵撤离点/夺舍流 (蹲守/掠夺)": {
            "suitability": "A",
            "reason": "完美的“老六”干员，静音、致盲、追踪、延缓救援，一套完整的偷袭与削弱组合。",
            "strategy": "开启静默潜袭埋伏，用飞行器自动索敌或补刀，闪光弹致盲后偷袭。被动让被击倒的敌人更难被救起。",
            "core_advantage": "静音偷袭与战斗减益。"
          },
          "猛攻流 (正面作战)": {
            "suitability": "B",
            "reason": "在正面交战中作用有限，更偏向单人偷袭而非团队推进。",
            "strategy": "利用飞行器压制拐角敌人，闪光弹辅助突破。静默潜袭在特定战术迂回中有奇效。",
            "core_advantage": "侧面骚扰与单体控制。"
          }
        }
      },
      {
        "id": "ji_feng",
        "name": "疾风（克莱尔·安·拜尔斯）",
        "type": "突击",
        "skills": {
          "main": "背部辅助脊椎：实现8方向快速翻滚，躲避子弹。",
          "second": "钻墙电刺：发射可穿透薄掩体的电击，麻痹敌人并击飞其武器。",
          "throwable": "紧急回避装置：放置一个锚点，再次激活可瞬间拉回至锚点位置并回复部分生命值。",
          "passive": "灵活身法：翻滚后短时间内提升移动速度。"
        },
        "background": "S5赛季登场的高机动干员，适合突入和灵活拉扯。",
        "suitable_for_players": {
          "鼠鼠 (避战/捡漏)": {
            "suitability": "B",
            "reason": "极强的生存和脱战能力，但操作要求较高。",
            "strategy": "利用翻滚和回避装置从各种围剿中逃脱。电刺可短暂阻止追击的敌人。",
            "core_advantage": "顶尖的生存与逃脱能力。"
          },
          "堵撤离点/夺舍流 (蹲守/掠夺)": {
            "suitability": "B",
            "reason": "灵活有余但爆发和控制不足，不如专精偷袭的干员直接。",
            "strategy": "利用高机动性在复杂地形周旋，电刺隔墙偷袭。",
            "core_advantage": "高机动性创造偷袭机会。"
          },
          "猛攻流 (正面作战)": {
            "suitability": "A+",
            "reason": "版本强势突击手，极高的操作上限，在高手手中是难以捉摸的战场幽灵。",
            "strategy": "利用翻滚无敌帧规避关键伤害，切入敌阵扰乱阵型。电刺克制掩体后的敌人。回避装置提供二次进场或紧急回复能力。",
            "core_advantage": "高操作上限的机动战神。"
          }
        }
      },
      {
        "id": "feng_yi",
        "name": "蜂医（罗伊·斯米）",
        "type": "支援",
        "skills": {
          "main": "激素枪：远程治疗多名队友或自我恢复，开镜可扣除敌人血量。",
          "second": "烟幕无人机：喷射15米烟雾长廊，分割战场或提供掩护。",
          "throwable": "蜂巢科技烟雾弹：投掷后形成烟雾，激素枪射击可转为绿色治疗烟雾。",
          "passive": "高效救援：1.4秒快速救起倒地队友，并移除血量上限削减效果。"
        },
        "background": "战地医生，早期唯一支援角色，团队生存保障核心。",
        "suitable_for_players": {
          "鼠鼠 (避战/捡漏)": {
            "suitability": "S",
            "reason": "跑刀之王。自我治疗减少药品消耗，超长烟雾提供绝对安全的撤离路径。",
            "strategy": "不追求战斗，专注搜刮。被盯上或需要撤离时，铺设烟雾长廊直接跑路。激素枪自疗维持状态。",
            "core_advantage": "自我续航与无敌烟雾撤离。"
          },
          "堵撤离点/夺舍流 (蹲守/掠夺)": {
            "suitability": "B",
            "reason": "治疗和烟雾对蹲守偷袭帮助有限，缺乏先手优势。",
            "strategy": "烟雾可以遮蔽自己埋伏的位置，或用于夺舍后遮挡视线逃跑。激素枪保证埋伏时的状态。",
            "core_advantage": "提供战术烟雾掩护。"
          },
          "猛攻流 (正面作战)": {
            "suitability": "A",
            "reason": "团队作战的核心辅助，强大的治疗、救援和战场分割能力。",
            "strategy": "在后方提供持续治疗，快速拉起倒地的核心队友。用烟雾阻断敌方火力线或掩护团队转移。",
            "core_advantage": "团队持续作战与战术控场能力。"
          }
        }
      },
      {
        "id": "gu",
        "name": "蛊（佐娅·庞琴科娃）",
        "type": "支援",
        "skills": {
          "main": "致盲毒雾：投掷后生成一片干扰敌人视野的毒雾。",
          "second": "肾上腺素激活：为队友提升枪械控制能力（后坐力降低）。",
          "throwable": "“流荧”集群系统：释放无人机群，降低范围内敌人的听觉、视觉并削弱其生命值上限。",
          "passive": "快速治疗：缩短治疗队友所需的时间。"
        },
        "background": "支援型干员，擅长通过神经化学与无人机技术削弱敌人、支援团队。",
        "suitable_for_players": {
          "鼠鼠 (避战/捡漏)": {
            "suitability": "C",
            "reason": "技能更偏向团队辅助和进攻削弱，对个人生存跑路帮助不大。",
            "strategy": "“流荧”可以丢在身后阻碍追兵，毒雾干扰视野方便逃跑。",
            "core_advantage": "有限的逃跑阻碍能力。"
          },
          "堵撤离点/夺舍流 (蹲守/掠夺)": {
            "suitability": "A",
            "reason": "出色的削弱与控制能力，能极大增加偷袭成功率和降低目标反抗能力。",
            "strategy": "在埋伏点提前布置“流荧”，大幅削弱进入区域的敌人。毒雾致盲后出击。肾上腺素在夺舍后对枪时提供增益。",
            "core_advantage": "强大的区域削弱与控场。"
          },
          "猛攻流 (正面作战)": {
            "suitability": "S",
            "reason": "顶级团队辅助，集软控、硬削弱、团队增益于一体，能显著提升团队交战胜率。",
            "strategy": "交战前用“流荧”削弱一片区域，配合团队压上。毒雾封锁关键路口或房间。肾上腺素关键时刻提升团队枪法。",
            "core_advantage": "团队进攻的“力量倍增器”。"
          }
        }
      },
      {
        "id": "die",
        "name": "蝶（莉娜·范德梅尔）",
        "type": "支援",
        "skills": {
          "main": "“蝶式”救援无人机：释放无人机群，自动寻找并治疗周围倒地友军，随后需靠近激活完成救援。释放期间获得伤害吸收护盾。",
          "second": "纳米粉尘医疗：投掷锁定队友的无人机，播撒粉尘治疗区域中的友军。",
          "throwable": "遥控烟雾：通过手势引导投掷方向，形成大型烟雾。",
          "passive": "体征检测：延长小队成员的倒地计时；使用纳米医疗时能看到队友健康状态。"
        },
        "background": "前哈夫克研究员，叛逃后成为医疗干员，主打远程救援、持续治疗与战术控场。",
        "suitable_for_players": {
          "鼠鼠 (避战/捡漏)": {
            "suitability": "B",
            "reason": "强大的自我和团队治疗能力，遥控烟雾提供出色撤离掩护。",
            "strategy": "用纳米粉尘自我维持状态。遥控烟雾实现超远距离精准封烟，规划安全路线。",
            "core_advantage": "超远程精准烟雾与自我治疗。"
          },
          "堵撤离点/夺舍流 (蹲守/掠夺)": {
            "suitability": "C",
            "reason": "技能组偏向后手救援和治疗，与先手偷袭的玩法不匹配。",
            "strategy": "遥控烟雾可用于遮蔽或干扰，但效果不如蜂医直接。",
            "core_advantage": "战术烟雾应用。"
          },
          "猛攻流 (正面作战)": {
            "suitability": "A+",
            "reason": "顶级的战地医护兵，提供远程、安全且高效的救援和治疗，极大提升团队容错率。",
            "strategy": "在安全位置远程救援倒地的突击手，避免救人者暴毙。纳米粉尘维持前线血线。遥控烟雾进行战术分割。",
            "core_advantage": "安全高效的远程支援与救援。"
          }
        }
      },
      {
        "id": "lu_na",
        "name": "露娜（金卢娜）",
        "type": "侦察",
        "skills": {
          "main": "探测箭矢：发射后侦查沿途未被掩体遮挡的敌人，向空中发射可触发特殊扫描。",
          "second": "电击箭矢：命中区域后持续释放电流造成伤害和干扰。",
          "throwable": "破片手雷：双模式杀伤，穿透护甲。",
          "passive": "敌情分析：攻击敌方后短暂标记其位置。"
        },
        "background": "前情报官与职业运动员，侦察干员，擅长信息分析与箭术。",
        "suitable_for_players": {
          "鼠鼠 (避战/捡漏)": {
            "suitability": "A",
            "reason": "顶尖的信息获取能力，能提前预知危险，完美规避战斗。",
            "strategy": "向行进路线或资源点发射探测箭，确认安全后再前进。电击箭可封锁身后通道拖延追兵。",
            "core_advantage": "全游戏最强的单人预警能力。"
          },
          "堵撤离点/夺舍流 (蹲守/掠夺)": {
            "suitability": "S",
            "reason": "信息就是一切。探测箭掌握区域动态，电击箭控制出口，被动标记便于追击。",
            "strategy": "在埋伏点用探测箭监视大片区域，掌握猎物动向。电击箭放在敌人必经之路上制造伤害和混乱。",
            "core_advantage": "埋伏区域的绝对信息掌控。"
          },
          "猛攻流 (正面作战)": {
            "suitability": "A",
            "reason": "优秀的团队信息位，能为队伍提供关键敌方位置，辅助攻坚。",
            "strategy": "开战前用探测箭摸清敌人布防。电击箭压制掩体后的敌人。被动标记帮助团队集火。",
            "core_advantage": "团队进攻的信息先锋。"
          }
        }
      },
      {
        "id": "hai_zhua",
        "name": "骇爪（麦晓雯）",
        "type": "侦察",
        "skills": {
          "main": "信号破译器：扫描敌方电子信号，显示最多6名敌人实时位置及轨迹。",
          "second": "闪光巡飞器：沿轨迹飞行的无人机，触敌后致盲。",
          "throwable": "数据飞刀：投掷电子飞镖，造成伤害或禁用电子设备（如敌方无人机）。",
          "passive": "隐匿消声：提升移动隐蔽性，降低被探测概率。"
        },
        "background": "顶尖电子攻防专家，侦察干员，擅长电子战与信息压制。",
        "suitable_for_players": {
          "鼠鼠 (避战/捡漏)": {
            "suitability": "A",
            "reason": "全图透视“级信息能力，被动静步，是“信息鼠”的顶级选择。",
            "strategy": "开局或进入新区城前开大，掌握全图玩家动态，完美规划安全路径。静步移动更不易被发现。",
            "core_advantage": "全图雷达“与增强隐蔽性。"
          },
          "堵撤离点/夺舍流 (蹲守/掠夺)": {
            "suitability": "A+",
            "reason": "大招能揭示所有敌人动向，便于选择最肥的猎物或避开多人队伍。",
            "strategy": "在关键时段开启大招，选择落单或携带高级装备的玩家作为目标。闪光巡飞器用于先手致盲。",
            "core_advantage": "猎人“的终极瞄准镜。"
          },
          "猛攻流 (正面作战)": {
            "suitability": "S",
            "reason": "战略级信息干员，大招能彻底改变战局，让团队掌握绝对主动权。",
            "strategy": "团战前或突击前开启大招，实现战术透明化。闪光巡飞器辅助突破，数据飞刀针对敌方工程设备。",
            "core_advantage": "战争迷雾“驱散者，团队信息核心。"
          }
        }
      },
      {
        "id": "yin_yi",
        "name": "银翼（兰登·哈里森）",
        "type": "侦察",
        "skills": {
          "main": "猎鹰仿生无人机：召唤无人机标记其视野内所有敌人位置。",
          "second": "蜂鸟间谍摄像头：投掷后可黏附在敌人头盔上，获取其团队视野和踪迹。",
          "throwable": "脉冲手雷：投掷后瘫痪范围内敌方电子设备。",
          "passive": "足迹追踪：能探查敌人留下的脚印，获取其装备和位置信息。"
        },
        "background": "S6赛季上线的侦察干员，擅长电子信息设备与情报获取。",
        "suitable_for_players": {
          "鼠鼠 (避战/捡漏)": {
            "suitability": "B",
            "reason": "信息能力较强，但不如露娜和骇爪直接高效。被动追踪有一定预警作用。",
            "strategy": "用猎鹰无人机侦察前方区域。通过脚印判断是否有玩家刚经过，决定前进或绕路。",
            "core_advantage": "区域侦察与痕迹追踪。"
          },
          "堵撤离点/夺舍流 (蹲守/掠夺)": {
            "suitability": "A",
            "reason": "蜂鸟摄像头“是神技，标记一个等于标记一队，实现精准狩猎。",
            "strategy": "将蜂鸟摄像头投掷到可能经过的敌人身上，长期监视其整队动向。猎鹰无人机辅助掌控埋伏点周边情况。",
            "core_advantage": "附骨之疽“式的长期监视能力。"
          },
          "猛攻流 (正面作战)": {
            "suitability": "A",
            "reason": "提供灵活持续的信息支持，蜂鸟摄像头能打乱敌方部署。",
            "strategy": "开战前投放猎鹰无人机。尝试将蜂鸟贴到敌方关键干员（如奶妈）身上。脉冲手雷克制敌方工程和侦察设备。",
            "core_advantage": "持续的情报骚扰与压制。"
          }
        }
      },
      {
        "id": "mu_yang_ren",
        "name": "牧羊人（泰瑞·缪萨）",
        "type": "工程",
        "skills": {
          "main": "声波陷阱：部署于物体表面，触发后造成穿透伤害并减速敌人。",
          "second": "声波震慑：周期性压制范围内敌人的战斗能力（降低操控、开镜速度等）。",
          "throwable": "增强型破片手雷",
          "passive": "减震防御：降低受到的爆炸伤害。"
        },
        "background": "工程兵干员，定位于防守与反载具作战，擅长部署陷阱与区域控制。",
        "suitable_for_players": {
          "鼠鼠 (避战/捡漏)": {
            "suitability": "C",
            "reason": "技能偏向固定区域防御，与移动搜刮的玩法相悖。",
            "strategy": "可在计划撤离的点位或藏身房门口布置声波陷阱作为警报和最后防线。",
            "core_advantage": "有限的固定点位预警。"
          },
          "堵撤离点/夺舍流 (蹲守/掠夺)": {
            "suitability": "A",
            "reason": "完美的区域封锁大师，能让埋伏点变成死亡禁区。",
            "strategy": "在撤离点或通道布满声波陷阱作为警报和第一道杀伤。开启声波震慑领域，削弱进入区域的敌人后再出手收割。",
            "core_advantage": "请君入瓮“的陷阱大师。"
          },
          "猛攻流 (正面作战)": {
            "suitability": "B",
            "reason": "在进攻中作用有限，更擅长阵地防御和推进中的临时固守。",
            "strategy": "占领关键房间或资源点后，布设陷阱防止被偷屁股。声波震慑在防守狭窄路口时效果显著。",
            "core_advantage": "占领区的巩固与防守。"
          }
        }
      },
      {
        "id": "wu_lu_lu",
        "name": "乌鲁鲁（大卫·费莱尔）",
        "type": "工程",
        "skills": {
          "main": "巡飞弹：呼叫一架可遥控的巡飞弹进行远程精确打击。",
          "second": "速凝掩体：快速部署一个可穿透射击的临时掩体。",
          "throwable": "复合型燃烧弹：投掷后产生大范围持续燃烧区域。",
          "passive": "坚韧：对骨折和装备造成的减速效果有强抗性。"
        },
        "background": "工程干员，兼具防御与进攻能力，适合阵地战和远距离打击。",
        "suitable_for_players": {
          "鼠鼠 (避战/捡漏)": {
            "suitability": "D",
            "reason": "技能笨重且偏向主动交战，与避战思路完全不符。",
            "strategy": "几乎无适用场景。",
            "core_advantage": "无"
          },
          "堵撤离点/夺舍流 (蹲守/掠夺)": {
            "suitability": "B",
            "reason": "巡飞弹可用于超视距打击或补刀，燃烧弹封锁路径，但整体不如其他干员直接。",
            "strategy": "用巡飞弹攻击试图逃跑或躲藏的敌人。在敌人可能的逃跑路线上投掷燃烧弹。",
            "core_advantage": "远程消耗与路径封锁。"
          },
          "猛攻流 (正面作战)": {
            "suitability": "A",
            "reason": "强力的战术攻坚手，提供远程火力、即时掩体和区域封锁。",
            "strategy": "用巡飞弹精准打击敌方掩体后的高价值目标（如狙击手、支援）。速凝掩体在开阔地提供紧急掩护。燃烧弹压制房间或通道。",
            "core_advantage": "多功能战术攻坚与支援。"
          }
        }
      },
      {
        "id": "shen_lan",
        "name": "深蓝（阿列克谢·彼得罗夫）",
        "type": "工程",
        "skills": {
          "main": "重型防爆套装/全身盾：展开一面大盾吸引火力，盾牌可击倒近身敌人或反弹投掷物。",
          "second": "多功能钩爪枪：发射钩爪，可拉回敌人、队友或装备箱。",
          "throwable": "刀片刺网手雷：生成一片造成伤害和减速的刺网。",
          "passive": "后方防护：盾牌未使用时挂在背后，可抵挡来自后方的子弹。"
        },
        "background": "工程干员，代号“深蓝”，能为队友提供火力保护，是团队推进时的防护屏障。",
        "suitable_for_players": {
          "鼠鼠 (避战/捡漏)": {
            "suitability": "D",
            "reason": "技能组完全为团队正面推进设计，极度笨重，不适合单人行动。",
            "strategy": "几乎无适用场景。",
            "core_advantage": "无"
          },
          "堵撤离点/夺舍流 (蹲守/掠夺)": {
            "suitability": "C",
            "reason": "盾牌在蹲守时可能暴露位置，钩爪有奇效但操作难度高。",
            "strategy": "在狭窄通道用盾牌硬堵。尝试用钩爪将路过的敌人拉过来秒杀。",
            "core_advantage": "特定地形的绝对控制（风险高）。"
          },
          "猛攻流 (正面作战)": {
            "suitability": "S",
            "reason": "顶级团队盾牌，攻坚战和推进战的核心，能强行创造安全空间。",
            "strategy": "举盾为团队开辟道路，吸收火力。钩爪将关键敌人拉出掩体集火，或救援倒地的队友。刺网封锁侧翼。",
            "core_advantage": "人形装甲车，团队推进的绝对核心。"
          }
        }
      }
    ],
    "summary": {
      "selection_logic": {
        "鼠鼠": "核心需求是【生存】、【信息】、【撤离】。优选顺序：蜂医(生存撤离) > 骇爪/露娜(信息预警) > 威龙(机动逃生)。",
        "堵撤离点/夺舍流": "核心需求是【先手信息】、【爆发/控制】、【逃脱】。优选顺序：红狼(机动收割) > 露娜/骇爪(区域信息) > 无名/蛊(削弱控制)。",
        "猛攻流": "核心需求是【正面强度】、【团队贡献】、【信息】。优选顺序：威龙/疾风(突击核心) > 蛊/骇爪(团队辅助) > 深蓝/蜂医(防护治疗)。突击、支援、侦察、工程需均衡搭配。"
      },
      "note": "干员强度与地图、队伍构成密切相关。一个干员在不同玩家手中的上限差异巨大（如疾风）。选择时请结合自身玩法、地图特点及团队需求综合考虑。"
    }
  }